{
  "letters": [
    {"key": "a"},
    {"key": "b"},
    {"key": "c"},
    {"key": "d"},
    {"key": "e"},
    {"key": "f"},
    {"key": "g"},
    {"key": "h"},
    {"key": "i"},
    {"key": "j"},
    {"key": "k"},
    {"key": "l"},
    {"key": "m"},
    {"key": "n"},
    {"key": "o"},
    {"key": "p"},
    {"key": "q"},
    {"key": "r"},
    {"key": "s"},
    {"key": "t"},
    {"key": "Enter"},
    {"key": "u"},
    {"key": "v"},
    {"key": "w"},
    {"key": "x"},
    {"key": "y"},
    {"key": "z"},
    {"key": "⇐"}
  ],
  "solutions": [
    {"id": 1, "word": "ninja"},
    {"id": 2, "word": "grade"},
    {"id": 3, "word": "aroma"},
    {"id": 4, "word": "reino"},
    {"id": 5, "word": "relax"},
    {"id": 6, "word": "tempo"},
    {"id": 7, "word": "corte"},
    {"id": 8, "word": "somar"},
    {"id": 9, "word": "canal"},
    {"id": 10, "word": "radio"},
    {"id": 11, "word": "audio"},
    {"id": 12, "word": "tigre"},
    {"id": 13, "word": "cesta"},
    {"id": 14, "word": "pilha"},
    {"id": 15, "word": "raios"},
    {"id": 16, "word": "areia"}
  ]
}